wbmailing/__init__.py
wbmailing/admin.py
wbmailing/apps.py
wbmailing/backend.py
wbmailing/celery.py
wbmailing/dynamic_preferences_registry.py
wbmailing/factories.py
wbmailing/tasks.py
wbmailing/urls.py
wbmailing/filters/__init__.py
wbmailing/filters/mailing_lists.py
wbmailing/filters/mails.py
wbmailing/locale/de/LC_MESSAGES/django.po
wbmailing/management/__init__.py
wbmailing/migrations/0001_initial_squashed_squashed_0008_alter_mail_bcc_email_alter_mail_cc_email_and_more.py
wbmailing/migrations/0002_delete_mailingsettings.py
wbmailing/migrations/0003_alter_mailinglistsubscriberchangerequest_options.py
wbmailing/migrations/__init__.py
wbmailing/models/__init__.py
wbmailing/models/mailing_lists.py
wbmailing/models/mails.py
wbmailing/serializers/__init__.py
wbmailing/serializers/mailing_lists.py
wbmailing/serializers/mails.py
wbmailing/templates/email_base_template.html
wbmailing/templates/template.html
wbmailing/templates/test.html
wbmailing/templates/workbench.html
wbmailing/templates/mailing/maintain_mail_subsciptions.html
wbmailing/templates/mailing/manage_mailing_list_subscriptions.html
wbmailing/templatetags/__init__.py
wbmailing/templatetags/mailing_tags.py
wbmailing/tests/__init__.py
wbmailing/tests/conftest.py
wbmailing/tests/signals.py
wbmailing/tests/test_serializers.py
wbmailing/tests/test_tasks.py
wbmailing/tests/test_viewsets.py
wbmailing/tests/tests.py
wbmailing/tests/models/__init__.py
wbmailing/tests/models/test_mailing_lists.py
wbmailing/tests/models/test_mails.py
wbmailing/viewsets/__init__.py
wbmailing/viewsets/analytics.py
wbmailing/viewsets/mailing_lists.py
wbmailing/viewsets/mails.py
wbmailing/viewsets/buttons/__init__.py
wbmailing/viewsets/buttons/mailing_lists.py
wbmailing/viewsets/buttons/mails.py
wbmailing/viewsets/display/__init__.py
wbmailing/viewsets/display/mailing_lists.py
wbmailing/viewsets/display/mails.py
wbmailing/viewsets/endpoints/__init__.py
wbmailing/viewsets/endpoints/mailing_lists.py
wbmailing/viewsets/endpoints/mails.py
wbmailing-2.2.6.dist-info/METADATA
wbmailing-2.2.6.dist-info/WHEEL
wbmailing-2.2.6.dist-info/RECORD
